pywebapi/__init__.py
pywebapi/_util.py
pywebapi/cors.py
pywebapi/fmtr.py
pywebapi/func.py
pywebapi-0.1a6.dist-info/LICENSE
pywebapi-0.1a6.dist-info/METADATA
pywebapi-0.1a6.dist-info/WHEEL
pywebapi-0.1a6.dist-info/top_level.txt
pywebapi-0.1a6.dist-info/RECORD
