Metadata-Version: 2.1
Name: pywebapi
Version: 0.1a6
Summary: PyWebApi is a micro-framework for Python RESTfulization. It turns Python(3+) modules/scripts into Web API (RESTful Service) out of the box.
Home-page: https://github.com/DataBooster/PyWebApi
Author: Abel Cheng
Author-email: abelcys@gmail.com
License: MIT
Keywords: RESTful,Service,WebAPI,IIS,JSON,DataBooster,Python,module_level_function,HTTP
Platform: any
Requires-Python: >=3
Requires-Dist: bottle
